onn512/__init__.py
onn512-0.0.3.dist-info/METADATA
onn512-0.0.3.dist-info/WHEEL
onn512-0.0.3.dist-info/top_level.txt
onn512-0.0.3.dist-info/RECORD
